[
  {
    "div": "w-[100px] h-[100px] rounded-full absolute z-50 overflow-hidden",
    "image": {
      "width": "500",
      "height": "500",
      "alt": "memberPicture1",
      "className": "object-cover w-full h-full",
      "src": "/static/committee/2023/Pasan_Prasident.jpg"
    }
  },
  {
    "div": "w-[90px] h-[90px] rounded-full absolute animate-north-west overflow-hidden z-40",
    "image": {
      "width": "500",
      "height": "500",
      "alt": "memberPicture2",
      "className": "object-cover w-full h-full",
      "src": "/static/committee/2023/Udayanga_Vice President.jpg"
    }
  },
  {
    "div": "w-[90px] h-[90px] rounded-full absolute animate-south overflow-hidden z-40",
    "image": {
      "width": "500",
      "height": "500",
      "alt": "memberPicture3",
      "className": "object-cover w-full h-full",
      "src": "/static/committee/2023/Sandali_Secretary.jpg"
    }
  },
  {
    "div": "w-[60px] h-[60px] rounded-full absolute animate-north overflow-hidden",
    "image": {
      "width": "500",
      "height": "500",
      "alt": "memberPicture4",
      "className": "object-cover w-full h-full",
      "src": "/static/committee/2023/Raveesha_AssistantSecretary.jpg"
    }
  },
  {
    "div": "w-[60px] h-[60px] rounded-full absolute animate-south-west overflow-hidden",
    "image": {
      "width": "500",
      "height": "500",
      "alt": "memberPicture5",
      "className": "object-cover w-full h-full",
      "src": "/static/committee/2023/Hirudika_Treasurer.jpg"
    }
  },
  {
    "div": "w-[60px] h-[60px] rounded-full absolute animate-north-east overflow-hidden",
    "image": {
      "width": "500",
      "height": "500",
      "alt": "memberPicture6",
      "className": "object-cover w-full h-full",
      "src": "/static/committee/2023/Tharush _ Assistant Treasurer .jpg"
    }
  },
  {
    "div": "w-[50px] h-[50px] rounded-full absolute animate-east overflow-hidden",
    "image": {
      "width": "500",
      "height": "500",
      "alt": "memberPicture7",
      "className": "object-cover w-full h-full",
      "src": "/static/committee/2023/Vikash_Media Coordinator.jpeg"
    }
  },
  {
    "div": "w-[50px] h-[50px] rounded-full absolute animate-south-east overflow-hidden",
    "image": {
      "width": "500",
      "height": "500",
      "alt": "memberPicture8",
      "className": "object-cover w-full h-full",
      "src": "/static/committee/2023/Thinuka_Editor.JPG"
    }
  }
]